mibibio/__init__.py
mibibio/my_module.py
mibibio-0.0.3.dist-info/licenses/LICENSE
mibibio-0.0.3.dist-info/METADATA
mibibio-0.0.3.dist-info/WHEEL
mibibio-0.0.3.dist-info/top_level.txt
mibibio-0.0.3.dist-info/RECORD
